Workbook
Name Cons_end: [1]Assumptions!$E$9
Name Cons_start: [1]Assumptions!$E$7
Name Model_Start: [1]Assumptions!$E$5
Name Mths_in_Qtr: [1]Assumptions!$E$16
Name Mths_in_Yr: [1]Assumptions!$E$19
Name Ops_end: [1]Assumptions!$E$13
Name Ops_start: [1]Assumptions!$E$11

Sheet PnL
A1: Profit & Loss for 2025/26 | AD1: Notes Intern
A2: Notes on the right
C3: Month: | D3: 1 | E3: =+D3+1 -> 2 | F3: =+E3+1 -> 3 | G3: =+F3+1 -> 4 | H3: =+G3+1 -> 5 | I3: =+H3+1 -> 6 | J3: =+I3+1 -> 7 | K3: =+J3+1 -> 8 | L3: =+K3+1 -> 9 | ... AA3: =+Z3+1 -> 24
B5: Revenue
C6: Conversion Funnel | D6: Up
C7: Monthly Users | D7: 2500 | E7: =+D7*(1+Input!$C$3) -> 2625 | F7: =+E7*(1+Input!$C$3) -> 2756.25 | G7: =+F7*(1+Input!$C$3) -> 2894.0625 | H7: =+G7*(1+Input!$C$3) -> 3038.7656 | I7: =+H7*(1+Input!$C$3) -> 3190.7039 | J7: =+I7*(1+Input!$C$3) -> 3350.2391 | K7: =+J7*(1+Input!$C$3) -> 3517.7511 | L7: =+K7*(1+Input!$C$3) -> 3693.6386 | ... AA7: =+Z7*(1+Input!$C$3) -> 7678.8094 | AE7: Target Social Media Ads (500-750 Users; Micro Influencers (100-250 Users); Organic Channels (350-750 Users)
C8: Conversion Rate | D8: 0.02 | E8: 0.02 | F8: 0.02 | G8: 0.02 | H8: 0.02 | I8: 0.02 | J8: 0.02 | K8: 0.02 | L8: 0.02 | M8: 0.02 | N8: 0.02 | O8: 0.02 | P8: 0.02 | Q8: 0.02 | R8: 0.02 | S8: 0.02 | T8: 0.02 | U8: 0.02 | V8: 0.02 | W8: 0.02 | X8: 0.02 | Y8: 0.02 | Z8: 0.02 | AA8: 0.02
C9: Mediated Bookings | D9: =+D7*D8 -> 50 | E9: =+E7*E8 -> 52.5 | F9: =+F7*F8 -> 55.125 | G9: =+G7*G8 -> 57.88125 | H9: =+H7*H8 -> 60.775312 | I9: =+I7*I8 -> 63.814078 | J9: =+J7*J8 -> 67.004782 | K9: =+K7*K8 -> 70.355021 | ... AA9: =+AA7*AA8 -> 153.57619
C10: Comission per Booking | D10: =$AH$10*$AH$11 -> 48 | E10: =$AH$10*$AH$11 -> 48 | F10: =$AH$10*$AH$11 -> 48 | G10: =$AH$10*$AH$11 -> 48 | H10: =$AH$10*$AH$11 -> 48 | I10: =$AH$10*$AH$11 -> 48 | J10: =$AH$10*$AH$11 -> 48 | K10: =$AH$10*$AH$11 -> 48 | ... AA10: =$AH$10*$AH$11 -> 48 | AE10: ⌀ Kosten Familienurlaub ab 3 Personen | AH10: 1600
C11: Total Revenue | D11: =+D9*D10 -> 2400 | E11: =+E9*E10 -> 2520 | F11: =+F9*F10 -> 2646 | G11: =+G9*G10 -> 2778.3 | H11: =+H9*H10 -> 2917.215 | I11: =+I9*I10 -> 3063.0758 | J11: =+J9*J10 -> 3216.2295 | K11: =+K9*K10 -> 3377.041 | ... AA11: =+AA9*AA10 -> 7371.657 | AE11: % Kommission pro Buchung | AH11: 0.03
B13: Operational expenditure
C14: Sales & Marketing Cost
C15: Social Media Marketing Budget | D15: 500 | E15: =+PnL!D15*(1+Input!$C$4) -> 525 | F15: =+PnL!E15*(1+Input!$C$4) -> 551.25 | G15: =+PnL!F15*(1+Input!$C$4) -> 578.8125 | H15: =+PnL!G15*(1+Input!$C$4) -> 607.75313 | I15: =+PnL!H15*(1+Input!$C$4) -> 638.14078 | J15: =+PnL!I15*(1+Input!$C$4) -> 670.04782 | K15: =+PnL!J15*(1+Input!$C$4) -> 703.55021 | L15: =+PnL!K15*(1+Input!$C$4) -> 738.72772 | ... AA15: =+PnL!Z15*(1+Input!$C$4) -> 1535.7619 | AE15: Micro-Influencer Partnerships in the beginning and own content creation
C16: Content Creation (Grafics, Videos, et cetera) | D16: 250 | E16: 250 | F16: 250 | G16: 250 | H16: 250 | I16: 250 | J16: 250 | K16: 250 | L16: 250 | M16: 250 | N16: 250 | O16: 250 | P16: 250 | Q16: 250 | R16: 250 | S16: 250 | T16: 250 | U16: 250 | V16: 250 | W16: 250 | X16: 250 | Y16: 250 | Z16: 250 | AA16: 250 | AE16: Own Content Creation - Short videos et cetera
C17: Total Marketing | D17: =+D15+D16 -> 750 | E17: =+E15+E16 -> 775 | F17: =+F15+F16 -> 801.25 | G17: =+G15+G16 -> 828.8125 | H17: =+H15+H16 -> 857.75313 | I17: =+I15+I16 -> 888.14078 | J17: =+J15+J16 -> 920.04782 | K17: =+K15+K16 -> 953.55021 | ... AA17: =+AA15+AA16 -> 1785.7619
C19: Production
C20: Chat GPT Requests/ Running Cost
C21: Chat GPT Request per User Request | D21: 3 | E21: 3 | F21: 3 | G21: 3 | H21: 3 | I21: 3 | J21: 3 | K21: 3 | L21: 3 | M21: 3 | N21: 3 | O21: 3 | P21: =+O21*2 -> 6 | Q21: 6 | R21: 6 | S21: 6 | T21: 6 | U21: 6 | V21: 6 | W21: 6 | X21: 6 | Y21: 6 | Z21: 6 | AA21: 6
C22: Cost per Request | D22: 0.01 | E22: 0.01 | F22: 0.01 | G22: 0.01 | H22: 0.01 | I22: 0.01 | J22: 0.01 | K22: 0.01 | L22: 0.01 | M22: 0.01 | N22: 0.01 | O22: 0.01 | P22: 0.01 | Q22: 0.01 | R22: 0.01 | S22: 0.01 | T22: 0.01 | U22: 0.01 | V22: 0.01 | W22: 0.01 | X22: 0.01 | Y22: 0.01 | Z22: 0.01 | AA22: 0.01
C23: Total AI-Cost | D23: =+D21*D22*D7 -> 75 | E23: =+E21*E22*E7 -> 78.75 | F23: =+F21*F22*F7 -> 82.6875 | G23: =+G21*G22*G7 -> 86.821875 | H23: =+H21*H22*H7 -> 91.162969 | I23: =+I21*I22*I7 -> 95.721117 | J23: =+J21*J22*J7 -> 100.50717 | K23: =+K21*K22*K7 -> 105.53253 | ... AA23: =+AA21*AA22*AA7 -> 460.72856
C25: Overhead
C26: Founders | D26: 4 | E26: 4 | F26: 4 | G26: 4 | H26: 4 | I26: 4 | J26: 4 | K26: 4 | L26: 4 | M26: 4 | N26: 4 | O26: 4 | P26: 4 | Q26: 4 | R26: 4 | S26: 4 | T26: 4 | U26: 4 | V26: 4 | W26: 4 | X26: 4 | Y26: 4 | Z26: 4 | AA26: 4
C27: Founders Salary* | D27: 2500 | E27: 2500 | F27: 2500 | G27: 2500 | H27: 2500 | I27: 2500 | J27: 2500 | K27: 2500 | L27: 2500 | M27: 2500 | N27: 2500 | O27: 2500 | P27: 3000 | Q27: 3000 | R27: 3000 | S27: 3000 | T27: 3000 | U27: 3000 | V27: 3000 | W27: 3000 | X27: 3000 | Y27: 3000 | Z27: 3000 | AA27: 3000 | AE27: Spätere Kompesation durch Gewinnausschüttungen
C28: Employer Gross (x1,27) | D28: =+D27*1.27 -> 3175 | E28: =+E27*1.27 -> 3175 | F28: =+F27*1.27 -> 3175 | G28: =+G27*1.27 -> 3175 | H28: =+H27*1.27 -> 3175 | I28: =+I27*1.27 -> 3175 | J28: =+J27*1.27 -> 3175 | K28: =+K27*1.27 -> 3175 | ... AA28: =+AA27*1.27 -> 3810
C29: Total Salary Founders | D29: =+D28*D26 -> 12700 | E29: =+E28*E26 -> 12700 | F29: =+F28*F26 -> 12700 | G29: =+G28*G26 -> 12700 | H29: =+H28*H26 -> 12700 | I29: =+I28*I26 -> 12700 | J29: =+J28*J26 -> 12700 | K29: =+K28*K26 -> 12700 | ... AA29: =+AA28*AA26 -> 15240
C31: Other Employees | D31: 0 | E31: 0 | F31: 0 | G31: 0 | H31: 0 | I31: 0 | J31: 0 | K31: 0 | L31: 0 | M31: 0 | N31: 0 | O31: 0 | P31: 0 | Q31: 0 | R31: 0 | S31: 0 | T31: 0 | U31: 0 | V31: 0 | W31: 0 | X31: 0 | Y31: 0 | Z31: 0 | AA31: 0
C32: Avg. Salary | D32: 0 | E32: 0 | F32: 0 | G32: 0 | H32: 0 | I32: 0 | J32: 0 | K32: 0 | L32: 0 | M32: 0 | N32: 0 | O32: 0 | P32: 0 | Q32: 0 | R32: 0 | S32: 0 | T32: 0 | U32: 0 | V32: 0 | W32: 0 | X32: 0 | Y32: 0 | Z32: 0 | AA32: 0
C33: Employer Gross (x1,27) | D33: =+D31*1.27 -> 0 | E33: =+E31*1.27 -> 0 | F33: =+F31*1.27 -> 0 | G33: =+G31*1.27 -> 0 | H33: =+H31*1.27 -> 0 | I33: =+I31*1.27 -> 0 | J33: =+J31*1.27 -> 0 | K33: =+K31*1.27 -> 0 | ... AA33: =+AA31*1.27 -> 0
C34: Total Salary Others | D34: =+D33*D31 -> 0 | E34: =+E33*E31 -> 0 | F34: =+F33*F31 -> 0 | G34: =+G33*G31 -> 0 | H34: =+H33*H31 -> 0 | I34: =+I33*I31 -> 0 | J34: =+J33*J31 -> 0 | K34: =+K33*K31 -> 0 | ... AA34: =+AA33*AA31 -> 0
C35: Human Resource Total | D35: =+D29+D34 -> 12700 | E35: =+E29+E34 -> 12700 | F35: =+F29+F34 -> 12700 | G35: =+G29+G34 -> 12700 | H35: =+H29+H34 -> 12700 | I35: =+I29+I34 -> 12700 | J35: =+J29+J34 -> 12700 | K35: =+K29+K34 -> 12700 | ... AA35: =+AA29+AA34 -> 15240
C37: PnL | D37: =D11-D17-D35 -> -11050 | E37: =E11-E17-E35 -> -10955 | F37: =F11-F17-F35 -> -10855.25 | G37: =G11-G17-G35 -> -10750.513 | H37: =H11-H17-H35 -> -10640.538 | I37: =I11-I17-I35 -> -10525.065 | J37: =J11-J17-J35 -> -10403.818 | K37: =K11-K17-K35 -> -10276.509 | ... AA37: =AA11-AA17-AA35 -> -9654.1049
C38: EBITDA | D38: =+D37 -> -11050 | E38: =+E37 -> -10955 | F38: =+F37 -> -10855.25 | G38: =+G37 -> -10750.513 | H38: =+H37 -> -10640.538 | I38: =+I37 -> -10525.065 | J38: =+J37 -> -10403.818 | K38: =+K37 -> -10276.509 | ... AA38: =+AA37 -> -9654.1049
C40: Dividends to Founders* | D40: =IF(D37>50000,D37*0.25,0) -> 0 | E40: =IF(E37>50000,E37*0.25,0) -> 0 | F40: =IF(F37>50000,F37*0.25,0) -> 0 | G40: =IF(G37>50000,G37*0.25,0) -> 0 | H40: =IF(H37>50000,H37*0.25,0) -> 0 | I40: =IF(I37>50000,I37*0.25,0) -> 0 | J40: =IF(J37>50000,J37*0.25,0) -> 0 | K40: =IF(K37>50000,K37*0.25,0) -> 0 | ... AA40: =IF(AA37>50000,AA37*0.25,0) -> 0 | AE40: Bei Gewinn > 50.000 werden anfänglich niedriges Gehalt durch Gewinnausschüttungen kompensiert
B42: Pre Money Bewertung - First Investment
C44: Monthly Revenue (Avg.) | D44: =AVERAGE(D11:AA11) -> 4450.1999 | F44: - Exceptional growh rate
C45: Yearly Revenue | D45: =D44*12 -> 53402.399 | F45: - Large adressable market
C46: Revenue-Multiple | D46: 20 | F46: - Strong customer retention
C47: Price | D47: =ROUNDUP(D45*D46,-5) -> 1100000
C49: 0.1 | D49: =ROUNDUP(D47*C49,-4) -> 110000

Sheet Input
A1: Inputs
B3: Monthly Growth Rate | C3: 0.05
B4: Marketing Budget Rate | C4: 0.05

Sheet Guide
A1: Guide
B3: About the model
B4: This section explains the purpose of the model
B5: Purpose
B6: ► | C6: The model is designed to provide a tutorial on how to incorporate a best practise cashflow waterfall in your financial models.
B8: Key
B9: This section describes the formatting used in the model
B10: Key model format
C11: Assumption | D11: 100 | F11: Cells that a user can change
C12: Technical_Input | D12: 100 | F12: Cells with inputs that should not be changed
C13: InSheet | D13: 100 | F13: Referencing cells from within sheet
C14: OffSheet | D14: 100 | F14: Referencing cells from a different sheet
C15: Line_Summary | D15: 100 | F15: Addition of all cells to the right
B16: Header format
C18: Header0 | D18: H0 Header0
C19: Header1 | D19: H1 Header1
C20: Header2 | D20: H2 Header2
C21: Header3 | D21: H3 Header3
C22: Header4 | D22: H4 Header4
C23: Sheet_Header | D23: SH Sheet_Header
C24: Table_Heading | D24: TA Table_Heading
B25: Cell format
C27: Comma [0] | D27: C0 Comma [0]
C28: Comma 2 | D28: C2 Comma 2
C29: Date | D29: DA Date
C30: Empty_Cell | D30: EM Empty_Cell
C31: Flag | D31: FL Flag
C32: InSheet | D32: IS InSheet
C33: Line_ClosingBal | D33: LC Line_ClosingBal
C34: Line_Operation | D34: LO Line_Operation
C35: Line_SubTotal | D35: LS Line_SubTotal
C36: Line_Total | D36: LT Line_Total
C37: Normal | D37: Normal
C38: Percent | D38: PE Percent
... C40: Unit | D40: UN Unit

Sheet Cashflow
A1: Cashflow

Sheet Bilanz
A1: Bilanz
F2: 2023 | G2: 2024 | H2: 2025 | I2: 2026 | J2: 2027
A3: Aktiva
C4: Anlagevermögen | E4: 000€
B5: Umlaufvermögen
C6: Barmittel (Kassenbestand) | E6: 000€
C7: Geldanlage | E7: 000€
C8: Forderungen aus Lieferungen und Leistungen | E8: 000€
C9: Lagerbestand (Vorräte) | E9: 000€
B10: Summe Umlaufvermögen | E10: 000€
A11: Summe Aktiva | E11: 000€
A13: Passiva
B14: Eigenkapital
C15: gezeichnetes Kapital | E15: 000€
C16: Eigenkapital (ohne gez. Kapital) | E16: 000€
C17: Gewinnrücklage inkl. Gewinn- / Verlustvorträge | E17: 000€
B18: Summe Eigenkapital | E18: 000€
B20: Verbindlichkeiten
C21: Verbindlichkeiten aus Lieferungen und Leistungen | E21: 000€
C22: Verbindlichkeiten gegenüber Kreditinstituten | E22: 000€
B23: Summe Verbindlichkeiten | E23: 000€
A24: Summe Passiva | E24: 000€
