Workbook
Name Cons_end: [1]Assumptions!$E$9
Name Cons_start: [1]Assumptions!$E$7
Name Model_Start: [1]Assumptions!$E$5
Name Mths_in_Qtr: [1]Assumptions!$E$16
Name Mths_in_Yr: [1]Assumptions!$E$19
Name Ops_end: [1]Assumptions!$E$13
Name Ops_start: [1]Assumptions!$E$11

Sheet P&L Vorlage
D2: 45658 | E2: 45689 | F2: 45717 | G2: 45748 | H2: 45778 | I2: 45809 | J2: 45839 | K2: 45870 | L2: 45901 | M2: 45931 | N2: 45962 | O2: 45992 | P2: 46023 | Q2: 46054 | R2: 46082 | S2: 46113 | T2: 46143 | U2: 46174 | V2: 46204 | W2: 46235 | X2: 46266 | Y2: 46296 | Z2: 46327 | AA2: 46357
B3: Profit & Loss
B4: Price | D4: 5 | E4: 5 | F4: 5 | G4: 15 | H4: 15 | I4: 15 | J4: 25 | K4: 25 | L4: 25 | M4: 25 | N4: 25 | O4: 25 | P4: 25 | Q4: 25 | R4: 25 | S4: 25 | T4: 25 | U4: 25 | V4: 25 | W4: 25 | X4: 25 | Y4: 25 | Z4: 25 | AA4: 25
B5: # Products Sold | D5: 0 | E5: 20 | F5: 20 | G5: 25 | H5: 15 | I5: 20 | J5: 20 | K5: 20 | L5: 20 | M5: 25 | N5: 25 | O5: 25 | P5: 25 | Q5: 25 | R5: 25 | S5: 25 | T5: 25 | U5: 25 | V5: 25 | W5: 25 | X5: 25 | Y5: 25 | Z5: 25 | AA5: 25
B7: Revenue | D7: =D5*D4 -> 0 | E7: =E5*E4 -> 100 | F7: =F5*F4 -> 100 | G7: =G5*G4 -> 375 | H7: =H5*H4 -> 225 | I7: =I5*I4 -> 300 | J7: =J5*J4 -> 500 | K7: =K5*K4 -> 500 | ... AA7: =AA5*AA4 -> 625
B9: Discounts | D9: 0 | E9: 0 | F9: 0 | G9: 0 | H9: 0 | I9: 0 | J9: 200 | K9: 300 | L9: 500 | M9: 0 | N9: 0 | O9: 0 | P9: 1 | Q9: 2 | R9: 3 | S9: 4 | T9: 5 | U9: 6 | V9: 7 | W9: 8 | X9: 9 | Y9: 10 | Z9: 11 | AA9: 12
B11: Sales & Marketing Cost | D11: =D12+D13 -> 800 | E11: =E12+E13 -> 1700 | F11: =F12+F13 -> 1700 | G11: =G12+G13 -> 1000 | H11: =H12+H13 -> 1700 | I11: =I12+I13 -> 1000 | J11: =J12+J13 -> 1000 | K11: =K12+K13 -> 1000 | ... AA11: =AA12+AA13 -> 1700
B12: Marketing | D12: 0 | E12: 900 | F12: 900 | G12: 900 | H12: 900 | I12: 900 | J12: 900 | K12: 900 | L12: 900 | M12: 900 | N12: 900 | O12: 900 | P12: 900 | Q12: 900 | R12: 900 | S12: 900 | T12: 900 | U12: 900 | V12: 900 | W12: 900 | X12: 900 | Y12: 900 | Z12: 900 | AA12: 900
B13: Sales | D13: 800 | E13: 800 | F13: 800 | G13: 100 | H13: 800 | I13: 100 | J13: 100 | K13: 100 | L13: 100 | M13: 800 | N13: 800 | O13: 800 | P13: 800 | Q13: 800 | R13: 800 | S13: 800 | T13: 800 | U13: 800 | V13: 800 | W13: 800 | X13: 800 | Y13: 800 | Z13: 800 | AA13: 800
B15: Production | D15: 20 | E15: 20 | F15: 20 | G15: 20 | H15: 20 | I15: 20 | J15: 20 | K15: 20 | L15: 20 | M15: 20 | N15: 20 | O15: 20 | P15: 20 | Q15: 20 | R15: 20 | S15: 20 | T15: 20 | U15: 20 | V15: 20 | W15: 20 | X15: 20 | Y15: 20 | Z15: 20 | AA15: 20
B18: Overhead | D18: =D19+D20 -> 2300 | E18: =E19+E20 -> 2300 | F18: =F19+F20 -> 2300 | G18: =G19+G20 -> 2300 | H18: =H19+H20 -> 2300 | I18: =I19+I20 -> 2300 | J18: =J19+J20 -> 2300 | K18: =K19+K20 -> 2300 | ... AA18: =AA19+AA20 -> 3000
B19: HR | D19: 2000 | E19: 2000 | F19: 2000 | G19: 2000 | H19: 2000 | I19: 2000 | J19: 2000 | K19: 2000 | L19: 2000 | M19: 2500 | N19: 2500 | O19: 2500 | P19: 2500 | Q19: 2500 | R19: 2500 | S19: 2500 | T19: 2500 | U19: 2500 | V19: 2500 | W19: 2500 | X19: 2500 | Y19: 2500 | Z19: 2500 | AA19: 2500
B20: General Cost | D20: 300 | E20: 300 | F20: 300 | G20: 300 | H20: 300 | I20: 300 | J20: 300 | K20: 300 | L20: 300 | M20: 500 | N20: 500 | O20: 500 | P20: 500 | Q20: 500 | R20: 500 | S20: 500 | T20: 500 | U20: 500 | V20: 500 | W20: 500 | X20: 500 | Y20: 500 | Z20: 500 | AA20: 500
B22: EBITDA | D22: =D7-D9-D11-D15-D18 -> -3120 | E22: =E7-E9-E11-E15-E18 -> -3920 | F22: =F7-F9-F11-F15-F18 -> -3920 | G22: =G7-G9-G11-G15-G18 -> -2945 | H22: =H7-H9-H11-H15-H18 -> -3795 | I22: =I7-I9-I11-I15-I18 -> -3020 | J22: =J7-J9-J11-J15-J18 -> -3020 | K22: =K7-K9-K11-K15-K18 -> -3120 | ... AA22: =AA7-AA9-AA11-AA15-AA18 -> -4107

Sheet PnL
A1: Profit & Loss for 2025/26 | AD1: Notes Intern
C3: Month: | D3: 1 | E3: =+D3+1 -> 2 | F3: =+E3+1 -> 3 | G3: =+F3+1 -> 4 | H3: =+G3+1 -> 5 | I3: =+H3+1 -> 6 | J3: =+I3+1 -> 7 | K3: =+J3+1 -> 8 | L3: =+K3+1 -> 9 | ... AA3: =+Z3+1 -> 24
C4: Date: | D4: 45809 | E4: 45839 | F4: 45870 | G4: 45901 | H4: 45931 | I4: 45962 | J4: 45992 | K4: 46023 | L4: 46054 | M4: 46082 | N4: 46113 | O4: 46143 | P4: 46174 | Q4: 46204 | R4: 46235 | S4: 46266 | T4: 46296 | U4: 46327 | V4: 46357 | W4: 46388 | X4: 46419 | Y4: 46447 | Z4: 46478 | AA4: 46508
B6: Revenue
C7: Conversion Funnel | D7: Up
C8: Monthly Users | D8: 2500 | E8: =+D8*(1+Input!$C$3) -> 2625 | F8: =+E8*(1+Input!$C$3) -> 2756.25 | G8: =+F8*(1+Input!$C$3) -> 2894.0625 | H8: =+G8*(1+Input!$C$3) -> 3038.7656 | I8: =+H8*(1+Input!$C$3) -> 3190.7039 | J8: =+I8*(1+Input!$C$3) -> 3350.2391 | K8: =+J8*(1+Input!$C$3) -> 3517.7511 | L8: =+K8*(1+Input!$C$3) -> 3693.6386 | ... AA8: =+Z8*(1+Input!$C$3) -> 7678.8094 | AE8: Target Social Media Ads (500-750 Users; Micro Influencers (100-250 Users); Organic Channels (350-750 Users)
C9: Conversion Rate | D9: 0.02 | E9: 0.02 | F9: 0.02 | G9: 0.02 | H9: 0.02 | I9: 0.02 | J9: 0.02 | K9: 0.02 | L9: 0.02 | M9: 0.02 | N9: 0.02 | O9: 0.02 | P9: 0.02 | Q9: 0.02 | R9: 0.02 | S9: 0.02 | T9: 0.02 | U9: 0.02 | V9: 0.02 | W9: 0.02 | X9: 0.02 | Y9: 0.02 | Z9: 0.02 | AA9: 0.02 | AE9: Indikation zu annahmen
C10: Mediated Bookings | D10: =+D8*D9 -> 50 | E10: =+E8*E9 -> 52.5 | F10: =+F8*F9 -> 55.125 | G10: =+G8*G9 -> 57.88125 | H10: =+H8*H9 -> 60.775312 | I10: =+I8*I9 -> 63.814078 | J10: =+J8*J9 -> 67.004782 | K10: =+K8*K9 -> 70.355021 | ... AA10: =+AA8*AA9 -> 153.57619
C11: Comission per Booking | D11: =$AH$11*$AH$12 -> 48 | E11: =$AH$11*$AH$12 -> 48 | F11: =$AH$11*$AH$12 -> 48 | G11: =$AH$11*$AH$12 -> 48 | H11: =$AH$11*$AH$12 -> 48 | I11: =$AH$11*$AH$12 -> 48 | J11: =$AH$11*$AH$12 -> 48 | K11: =$AH$11*$AH$12 -> 48 | ... AA11: =$AH$11*$AH$12 -> 48 | AE11: ⌀ Kosten Familienurlaub ab 3 Personen | AH11: 1600
C12: Total Revenue | D12: =+D10*D11 -> 2400 | E12: =+E10*E11 -> 2520 | F12: =+F10*F11 -> 2646 | G12: =+G10*G11 -> 2778.3 | H12: =+H10*H11 -> 2917.215 | I12: =+I10*I11 -> 3063.0758 | J12: =+J10*J11 -> 3216.2295 | K12: =+K10*K11 -> 3377.041 | ... AA12: =+AA10*AA11 -> 7371.657 | AE12: % Kommission pro Buchung | AH12: 0.03
B14: Operational expenditure
C15: Sales & Marketing Cost
C16: Social Media Marketing Budget | D16: 500 | E16: =+PnL!D16*(1+Input!$C$4) -> 525 | F16: =+PnL!E16*(1+Input!$C$4) -> 551.25 | G16: =+PnL!F16*(1+Input!$C$4) -> 578.8125 | H16: =+PnL!G16*(1+Input!$C$4) -> 607.75313 | I16: =+PnL!H16*(1+Input!$C$4) -> 638.14078 | J16: =+PnL!I16*(1+Input!$C$4) -> 670.04782 | K16: =+PnL!J16*(1+Input!$C$4) -> 703.55021 | L16: =+PnL!K16*(1+Input!$C$4) -> 738.72772 | ... AA16: =+PnL!Z16*(1+Input!$C$4) -> 1535.7619 | AE16: Micro-Influencer Partnerships in the beginning and own content creation
C17: Content Creation (Grafics, Videos, et cetera) | D17: 250 | E17: 250 | F17: 250 | G17: 250 | H17: 250 | I17: 250 | J17: 250 | K17: 250 | L17: 250 | M17: 250 | N17: 250 | O17: 250 | P17: 250 | Q17: 250 | R17: 250 | S17: 250 | T17: 250 | U17: 250 | V17: 250 | W17: 250 | X17: 250 | Y17: 250 | Z17: 250 | AA17: 250 | AE17: Own Content Creation - Short videos et cetera
C18: Total Marketing | D18: =+D16+D17 -> 750 | E18: =+E16+E17 -> 775 | F18: =+F16+F17 -> 801.25 | G18: =+G16+G17 -> 828.8125 | H18: =+H16+H17 -> 857.75313 | I18: =+I16+I17 -> 888.14078 | J18: =+J16+J17 -> 920.04782 | K18: =+K16+K17 -> 953.55021 | ... AA18: =+AA16+AA17 -> 1785.7619
C20: Production
C21: Chat GPT Requests/ Running Cost | AE21: Pre money bewertung
C22: Chat GPT Request per User Request | D22: 3 | E22: 3 | F22: 3 | G22: 3 | H22: 3 | I22: 3 | J22: 3 | K22: 3 | L22: 3 | M22: 3 | N22: 3 | O22: 3 | P22: =+O22*2 -> 6 | Q22: 6 | R22: 6 | S22: 6 | T22: 6 | U22: 6 | V22: 6 | W22: 6 | X22: 6 | Y22: 6 | Z22: 6 | AA22: 6 | AE22: einstieg investor
C23: Cost per Request | D23: 0.01 | E23: 0.01 | F23: 0.01 | G23: 0.01 | H23: 0.01 | I23: 0.01 | J23: 0.01 | K23: 0.01 | L23: 0.01 | M23: 0.01 | N23: 0.01 | O23: 0.01 | P23: 0.01 | Q23: 0.01 | R23: 0.01 | S23: 0.01 | T23: 0.01 | U23: 0.01 | V23: 0.01 | W23: 0.01 | X23: 0.01 | Y23: 0.01 | Z23: 0.01 | AA23: 0.01
C24: Total AI-Cost | D24: =+D22*D23*D8 -> 75 | E24: =+E22*E23*E8 -> 78.75 | F24: =+F22*F23*F8 -> 82.6875 | G24: =+G22*G23*G8 -> 86.821875 | H24: =+H22*H23*H8 -> 91.162969 | I24: =+I22*I23*I8 -> 95.721117 | J24: =+J22*J23*J8 -> 100.50717 | K24: =+K22*K23*K8 -> 105.53253 | ... AA24: =+AA22*AA23*AA8 -> 460.72856
C26: Overhead
C27: Founders | D27: 4 | E27: 4 | F27: 4 | G27: 4 | H27: 4 | I27: 4 | J27: 4 | K27: 4 | L27: 4 | M27: 4 | N27: 4 | O27: 4 | P27: 4 | Q27: 4 | R27: 4 | S27: 4 | T27: 4 | U27: 4 | V27: 4 | W27: 4 | X27: 4 | Y27: 4 | Z27: 4 | AA27: 4
C28: Founders Salary* | D28: 2500 | E28: 2500 | F28: 2500 | G28: 2500 | H28: 2500 | I28: 2500 | J28: 2500 | K28: 2500 | L28: 2500 | M28: 2500 | N28: 2500 | O28: 2500 | P28: 3000 | Q28: 3000 | R28: 3000 | S28: 3000 | T28: 3000 | U28: 3000 | V28: 3000 | W28: 3000 | X28: 3000 | Y28: 3000 | Z28: 3000 | AA28: 3000
C29: Employer Gross (x1,27) | D29: =+D28*1.27 -> 3175 | E29: =+E28*1.27 -> 3175 | F29: =+F28*1.27 -> 3175 | G29: =+G28*1.27 -> 3175 | H29: =+H28*1.27 -> 3175 | I29: =+I28*1.27 -> 3175 | J29: =+J28*1.27 -> 3175 | K29: =+K28*1.27 -> 3175 | ... AA29: =+AA28*1.27 -> 3810
C30: Total Salary Founders | D30: =+D29*D27 -> 12700 | E30: =+E29*E27 -> 12700 | F30: =+F29*F27 -> 12700 | G30: =+G29*G27 -> 12700 | H30: =+H29*H27 -> 12700 | I30: =+I29*I27 -> 12700 | J30: =+J29*J27 -> 12700 | K30: =+K29*K27 -> 12700 | ... AA30: =+AA29*AA27 -> 15240
C32: Other Employees | D32: 0 | E32: 0 | F32: 0 | G32: 0 | H32: 0 | I32: 0 | J32: 0 | K32: 0 | L32: 0 | M32: 0 | N32: 0 | O32: 0 | P32: 0 | Q32: 0 | R32: 0 | S32: 0 | T32: 0 | U32: 0 | V32: 0 | W32: 0 | X32: 0 | Y32: 0 | Z32: 0 | AA32: 0
C33: Avg. Salary | D33: 0 | E33: 0 | F33: 0 | G33: 0 | H33: 0 | I33: 0 | J33: 0 | K33: 0 | L33: 0 | M33: 0 | N33: 0 | O33: 0 | P33: 0 | Q33: 0 | R33: 0 | S33: 0 | T33: 0 | U33: 0 | V33: 0 | W33: 0 | X33: 0 | Y33: 0 | Z33: 0 | AA33: 0
C34: Employer Gross (x1,27) | D34: =+D32*1.27 -> 0 | E34: =+E32*1.27 -> 0 | F34: =+F32*1.27 -> 0 | G34: =+G32*1.27 -> 0 | H34: =+H32*1.27 -> 0 | I34: =+I32*1.27 -> 0 | J34: =+J32*1.27 -> 0 | K34: =+K32*1.27 -> 0 | ... AA34: =+AA32*1.27 -> 0
C35: Total Salary Others | D35: =+D34*D32 -> 0 | E35: =+E34*E32 -> 0 | F35: =+F34*F32 -> 0 | G35: =+G34*G32 -> 0 | H35: =+H34*H32 -> 0 | I35: =+I34*I32 -> 0 | J35: =+J34*J32 -> 0 | K35: =+K34*K32 -> 0 | ... AA35: =+AA34*AA32 -> 0
C36: Human Resource Total | D36: =+D30+D35 -> 12700 | E36: =+E30+E35 -> 12700 | F36: =+F30+F35 -> 12700 | G36: =+G30+G35 -> 12700 | H36: =+H30+H35 -> 12700 | I36: =+I30+I35 -> 12700 | J36: =+J30+J35 -> 12700 | K36: =+K30+K35 -> 12700 | ... AA36: =+AA30+AA35 -> 15240
B38: Funding costs
C40: PnL | D40: =D12-D18-D36 -> -11050 | E40: =E12-E18-E36 -> -10955 | F40: =F12-F18-F36 -> -10855.25 | G40: =G12-G18-G36 -> -10750.513 | H40: =H12-H18-H36 -> -10640.538 | I40: =I12-I18-I36 -> -10525.065 | J40: =J12-J18-J36 -> -10403.818 | K40: =K12-K18-K36 -> -10276.509 | ... AA40: =AA12-AA18-AA36 -> -9654.1049
C41: EBITDA | D41: =+D40 -> -11050 | E41: =+E40 -> -10955 | F41: =+F40 -> -10855.25 | G41: =+G40 -> -10750.513 | H41: =+H40 -> -10640.538 | I41: =+I40 -> -10525.065 | J41: =+J40 -> -10403.818 | K41: =+K40 -> -10276.509 | ... AA41: =+AA40 -> -9654.1049
C43: Dividends to Founders* | D43: =IF(D40>50000,D40*0.25,0) -> 0 | E43: =IF(E40>50000,E40*0.25,0) -> 0 | F43: =IF(F40>50000,F40*0.25,0) -> 0 | G43: =IF(G40>50000,G40*0.25,0) -> 0 | H43: =IF(H40>50000,H40*0.25,0) -> 0 | I43: =IF(I40>50000,I40*0.25,0) -> 0 | J43: =IF(J40>50000,J40*0.25,0) -> 0 | K43: =IF(K40>50000,K40*0.25,0) -> 0 | ... AA43: =IF(AA40>50000,AA40*0.25,0) -> 0 | AE43: Bei Gewinn > 50.000 werden anfänglich niedriges Gehalt durch Gewinnausschüttungen kompensiert

Sheet Input
A1: Inputs
B3: Monthly Growth Rate | C3: 0.05
B4: Marketing Budget Rate | C4: 0.05

Sheet Guide
A1: Guide
B3: About the model
B4: This section explains the purpose of the model
B5: Purpose
B6: ► | C6: The model is designed to provide a tutorial on how to incorporate a best practise cashflow waterfall in your financial models.
B8: Key
B9: This section describes the formatting used in the model
B10: Key model format
C11: Assumption | D11: 100 | F11: Cells that a user can change
C12: Technical_Input | D12: 100 | F12: Cells with inputs that should not be changed
C13: InSheet | D13: 100 | F13: Referencing cells from within sheet
C14: OffSheet | D14: 100 | F14: Referencing cells from a different sheet
C15: Line_Summary | D15: 100 | F15: Addition of all cells to the right
B16: Header format
C18: Header0 | D18: H0 Header0
C19: Header1 | D19: H1 Header1
C20: Header2 | D20: H2 Header2
C21: Header3 | D21: H3 Header3
C22: Header4 | D22: H4 Header4
C23: Sheet_Header | D23: SH Sheet_Header
C24: Table_Heading | D24: TA Table_Heading
B25: Cell format
C27: Comma [0] | D27: C0 Comma [0]
C28: Comma 2 | D28: C2 Comma 2
C29: Date | D29: DA Date
C30: Empty_Cell | D30: EM Empty_Cell
C31: Flag | D31: FL Flag
C32: InSheet | D32: IS InSheet
C33: Line_ClosingBal | D33: LC Line_ClosingBal
C34: Line_Operation | D34: LO Line_Operation
C35: Line_SubTotal | D35: LS Line_SubTotal
C36: Line_Total | D36: LT Line_Total
C37: Normal | D37: Normal
C38: Percent | D38: PE Percent
... C40: Unit | D40: UN Unit

Sheet Cashflow
A1: Cashflow

Sheet Bilanz
A1: Bilanz
F2: 2023 | G2: 2024 | H2: 2025 | I2: 2026 | J2: 2027
A3: Aktiva
C4: Anlagevermögen | E4: 000€
B5: Umlaufvermögen
C6: Barmittel (Kassenbestand) | E6: 000€
C7: Geldanlage | E7: 000€
C8: Forderungen aus Lieferungen und Leistungen | E8: 000€
C9: Lagerbestand (Vorräte) | E9: 000€
B10: Summe Umlaufvermögen | E10: 000€
A11: Summe Aktiva | E11: 000€
A13: Passiva
B14: Eigenkapital
C15: gezeichnetes Kapital | E15: 000€
C16: Eigenkapital (ohne gez. Kapital) | E16: 000€
C17: Gewinnrücklage inkl. Gewinn- / Verlustvorträge | E17: 000€
B18: Summe Eigenkapital | E18: 000€
B20: Verbindlichkeiten
C21: Verbindlichkeiten aus Lieferungen und Leistungen | E21: 000€
C22: Verbindlichkeiten gegenüber Kreditinstituten | E22: 000€
B23: Summe Verbindlichkeiten | E23: 000€
A24: Summe Passiva | E24: 000€
